v4API/Errors.py
v4API/Session.py
v4API/__init__.py
v4API-0.4.9.dist-info/METADATA
v4API-0.4.9.dist-info/WHEEL
v4API-0.4.9.dist-info/top_level.txt
v4API-0.4.9.dist-info/RECORD
